artigraph/__init__.py
artigraph/py.typed
artigraph/core/__init__.py
artigraph/core/db.py
artigraph/core/linker.py
artigraph/core/api/__init__.py
artigraph/core/api/artifact.py
artigraph/core/api/base.py
artigraph/core/api/filter.py
artigraph/core/api/funcs.py
artigraph/core/api/link.py
artigraph/core/api/node.py
artigraph/core/model/__init__.py
artigraph/core/model/_modeled_types.py
artigraph/core/model/base.py
artigraph/core/model/dataclasses.py
artigraph/core/model/filter.py
artigraph/core/orm/__init__.py
artigraph/core/orm/artifact.py
artigraph/core/orm/base.py
artigraph/core/orm/link.py
artigraph/core/orm/node.py
artigraph/core/serializer/__init__.py
artigraph/core/serializer/base.py
artigraph/core/serializer/datetime.py
artigraph/core/serializer/json.py
artigraph/core/storage/__init__.py
artigraph/core/storage/base.py
artigraph/core/storage/file.py
artigraph/core/utils/__init__.py
artigraph/core/utils/anysync.py
artigraph/core/utils/misc.py
artigraph/core/utils/type_hints.py
artigraph/extras/__init__.py
artigraph/extras/aws.py
artigraph/extras/networkx.py
artigraph/extras/numpy.py
artigraph/extras/pandas.py
artigraph/extras/plotly.py
artigraph/extras/polars.py
artigraph/extras/pyarrow.py
artigraph/extras/pydantic.py
artigraph-0.1.0.dist-info/METADATA
artigraph-0.1.0.dist-info/WHEEL
artigraph-0.1.0.dist-info/licenses/LICENSE.txt
artigraph-0.1.0.dist-info/RECORD
